fileserver_client/__init__.py
fileserver_client-1.0.0.dist-info/METADATA
fileserver_client-1.0.0.dist-info/WHEEL
fileserver_client-1.0.0.dist-info/top_level.txt
fileserver_client-1.0.0.dist-info/RECORD
