Metadata-Version: 2.4
Name: fileserver-client
Version: 1.0.0
Summary: Python client for FileServer API
Home-page: https://github.com/yourusername/fileserver
Author: FileServer Team
Keywords: fileserver,api,client
Classifier: Programming Language :: Python :: 3
Classifier: License :: OSI Approved :: MIT License
Classifier: Operating System :: OS Independent
Requires-Python: >=3.6
Requires-Dist: requests>=2.25.0
Dynamic: author
Dynamic: classifier
Dynamic: description
Dynamic: description-content-type
Dynamic: home-page
Dynamic: keywords
Dynamic: requires-dist
Dynamic: requires-python
Dynamic: summary
